ovos_skill_wikipedia/LICENSE
ovos_skill_wikipedia/MANIFEST.in
ovos_skill_wikipedia/README.md
ovos_skill_wikipedia/__init__.py
ovos_skill_wikipedia/pic.py
ovos_skill_wikipedia/version.py
ovos_skill_wikipedia/gui/all/jumping.gif
ovos_skill_wikipedia/locale/ca-es/MiscBlacklist.voc
ovos_skill_wikipedia/locale/ca-es/More.voc
ovos_skill_wikipedia/locale/ca-es/Weather.voc
ovos_skill_wikipedia/locale/ca-es/no entry found.dialog
ovos_skill_wikipedia/locale/ca-es/searching.dialog
ovos_skill_wikipedia/locale/ca-es/skill.json
ovos_skill_wikipedia/locale/ca-es/thats all.dialog
ovos_skill_wikipedia/locale/ca-es/wiki.intent
ovos_skill_wikipedia/locale/ca-es/wikiroulette.dialog
ovos_skill_wikipedia/locale/ca-es/wikiroulette.intent
ovos_skill_wikipedia/locale/da-dk/MiscBlacklist.voc
ovos_skill_wikipedia/locale/da-dk/More.voc
ovos_skill_wikipedia/locale/da-dk/Weather.voc
ovos_skill_wikipedia/locale/da-dk/no entry found.dialog
ovos_skill_wikipedia/locale/da-dk/searching.dialog
ovos_skill_wikipedia/locale/da-dk/skill.json
ovos_skill_wikipedia/locale/da-dk/thats all.dialog
ovos_skill_wikipedia/locale/da-dk/wiki.intent
ovos_skill_wikipedia/locale/da-dk/wikiroulette.dialog
ovos_skill_wikipedia/locale/da-dk/wikiroulette.intent
ovos_skill_wikipedia/locale/de-de/More.voc
ovos_skill_wikipedia/locale/de-de/Weather.voc
ovos_skill_wikipedia/locale/de-de/no entry found.dialog
ovos_skill_wikipedia/locale/de-de/searching.dialog
ovos_skill_wikipedia/locale/de-de/skill.json
ovos_skill_wikipedia/locale/de-de/thats all.dialog
ovos_skill_wikipedia/locale/de-de/wiki.intent
ovos_skill_wikipedia/locale/de-de/wikiroulette.dialog
ovos_skill_wikipedia/locale/de-de/wikiroulette.intent
ovos_skill_wikipedia/locale/en-us/MiscBlacklist.voc
ovos_skill_wikipedia/locale/en-us/More.voc
ovos_skill_wikipedia/locale/en-us/Weather.voc
ovos_skill_wikipedia/locale/en-us/no entry found.dialog
ovos_skill_wikipedia/locale/en-us/searching.dialog
ovos_skill_wikipedia/locale/en-us/skill.json
ovos_skill_wikipedia/ovos_skill_wikipedia.egg-info/PKG-INFO
ovos_skill_wikipedia/ovos_skill_wikipedia.egg-info/SOURCES.txt
ovos_skill_wikipedia/ovos_skill_wikipedia.egg-info/dependency_links.txt
ovos_skill_wikipedia/ovos_skill_wikipedia.egg-info/entry_points.txt
ovos_skill_wikipedia/ovos_skill_wikipedia.egg-info/requires.txt
ovos_skill_wikipedia/ovos_skill_wikipedia.egg-info/top_level.txt
ovos_skill_wikipedia-0.8.13.dist-info/LICENSE
ovos_skill_wikipedia-0.8.13.dist-info/METADATA
ovos_skill_wikipedia-0.8.13.dist-info/WHEEL
ovos_skill_wikipedia-0.8.13.dist-info/entry_points.txt
ovos_skill_wikipedia-0.8.13.dist-info/top_level.txt
ovos_skill_wikipedia-0.8.13.dist-info/RECORD
