Metadata-Version: 2.1
Name: ovos-skill-wikipedia
Version: 0.8.13
Summary: ovos wikipedia skill plugin
Home-page: https://github.com/OpenVoiceOS/ovos-skill-wikipedia
Author: JarbasAi
Author-email: jarbasai@mailfence.com
License: Apache-2.0
Keywords: ovos skill plugin
License-File: LICENSE
Requires-Dist: ovos-utils<1.0.0,>=0.7.0
Requires-Dist: ovos-workshop<8.0.0,>=3.4.0
Requires-Dist: ovos-wikipedia-solver<1.0.0,>=0.0.1
